regularizepsf-0.4.2.dist-info/top_level.txt
regularizepsf-0.4.2.dist-info/RECORD
regularizepsf-0.4.2.dist-info/LICENSE
regularizepsf-0.4.2.dist-info/METADATA
regularizepsf-0.4.2.dist-info/WHEEL
regularizepsf/helper.pyx
regularizepsf/visualize.py
regularizepsf/exceptions.py
regularizepsf/__init__.py
regularizepsf/helper.c
regularizepsf/helper.cpython-313-x86_64-linux-musl.so
regularizepsf/fitter.py
regularizepsf/psf.py
regularizepsf/corrector.py
