Metadata-Version: 2.1
Name: regularizepsf
Version: 0.4.2
Summary: Point spread function modeling and regularization
License: Copyright (c) 2024 PUNCH Science Operations Center
Requires-Python: >3.10
License-File: LICENSE
Requires-Dist: numpy
Requires-Dist: dill
Requires-Dist: h5py
Requires-Dist: lmfit
Requires-Dist: sep-pjw
Requires-Dist: cython
Requires-Dist: astropy
Requires-Dist: scipy
Requires-Dist: scikit-image
Requires-Dist: matplotlib
Requires-Dist: setuptools
Provides-Extra: test
Requires-Dist: pytest; extra == "test"
Requires-Dist: pytest-cov; extra == "test"
Requires-Dist: hypothesis; extra == "test"
Requires-Dist: coverage; extra == "test"
Requires-Dist: ruff; extra == "test"
Requires-Dist: pytest-mpl; extra == "test"
Provides-Extra: docs
Requires-Dist: sphinx; extra == "docs"
Requires-Dist: pydata-sphinx-theme; extra == "docs"
Requires-Dist: sphinx-autoapi; extra == "docs"
Provides-Extra: dev
Requires-Dist: regularizepsf[docs,test]; extra == "dev"
Requires-Dist: pre-commit; extra == "dev"
